{"entries":[{"name":"BattleCakes","uid":"8320ab78-0a40-50d0-89e7-df69b9db9dc9","platforms":[{"name":"Microsoft Windows","shortName":"Win"}],"releaseDate":"2024-03-01T00:00:00.000Z"},{"name":"Ufouria: The Saga 2","uid":"501fd8c6-dd1b-5e38-a6b2-fa4699b34795","platforms":[{"name":"Playstation 5","shortName":"PS5"},{"name":"Xbox Series X/S","shortName":"XBS"},{"name":"Nintendo Switch","shortName":"NS"},{"name":"Microsoft Windows","shortName":"Win"}],"releaseDate":"2024-03-01T00:00:00.000Z"},{"name":"Expeditions: A MudRunner Game","uid":"0616a490-217a-59bc-9c11-6d423ebdff55","platforms":[{"name":"Playstation 5","shortName":"PS5"},{"name":"Xbox Series X/S","shortName":"XBS"},{"name":"Playstation 4","shortName":"PS4"},{"name":"Xbox One","shortName":"XBO"},{"name":"Nintendo Switch","shortName":"NS"},{"name":"Microsoft Windows","shortName":"Win"}],"releaseDate":"2024-03-05T00:00:00.000Z"},{"name":"Quilts and Cats of Calico","uid":"8de2f85d-edaa-5863-8241-a14bdb3dcc41","platforms":[{"name":"Microsoft Windows","shortName":"Win"}],"releaseDate":"2024-03-05T00:00:00.000Z"},{"name":"The Outlast Trials","uid":"25652c9e-9af1-51e7-88df-0a45496e2ea7","platforms":[{"name":"Playstation 5","shortName":"PS5"},{"name":"Xbox Series X/S","shortName":"XBS"},{"name":"Playstation 4","shortName":"PS4"},{"name":"Xbox One","shortName":"XBO"},{"name":"Microsoft Windows","shortName":"Win"}],"releaseDate":"2024-03-05T00:00:00.000Z"},{"name":"S.T.A.L.K.E.R.: Legends of the Zone Trilogy","uid":"126a1cb1-87a2-5574-b9af-dcad117580df","platforms":[{"name":"Xbox One","shortName":"XBO"}],"releaseDate":"2024-03-06T00:00:00.000Z"},{"name":"As Dusk Falls","uid":"0bcb919f-2b8e-5509-82f7-9df9676323f5","platforms":[{"name":"Playstation 5","shortName":"PS5"},{"name":"Playstation 4","shortName":"PS4"}],"releaseDate":"2024-03-07T00:00:00.000Z"},{"name":"Snufkin: Melody of Moominvalley","uid":"63723280-0625-56da-8825-26e0e1115cdc","platforms":[{"name":"Nintendo Switch","shortName":"NS"},{"name":"Microsoft Windows","shortName":"Win"}],"releaseDate":"2024-03-07T00:00:00.000Z"},{"name":"The Pirate Queen: A Forgotten Legend","uid":"22642f2f-4469-5da1-915e-4404bb1e7ceb","platforms":[{"name":"Oculus Quest","shortName":"OQ"},{"name":"Microsoft Windows","shortName":"Win"}],"releaseDate":"2024-03-07T00:00:00.000Z"},{"name":"Akka Arrh","uid":"02ae0138-4e50-50a4-a46c-7285972cbe16","platforms":[{"name":"Playstation 5","shortName":"PS5"},{"name":"Playstation VR 2","shortName":"PSVR2"}],"releaseDate":"2024-03-08T00:00:00.000Z"},{"name":"Summerhouse","uid":"7bef398f-47d6-54f7-889d-e4fd112ce77f","platforms":[{"name":"Microsoft Windows","shortName":"Win"}],"releaseDate":"2024-03-08T00:00:00.000Z"},{"name":"Unicorn Overlord","uid":"5a689f2c-d1d8-59dc-b525-efdaca11e1d0","platforms":[{"name":"Playstation 5","shortName":"PS5"},{"name":"Xbox Series X/S","shortName":"XBS"},{"name":"Playstation 4","shortName":"PS4"},{"name":"Nintendo Switch","shortName":"NS"}],"releaseDate":"2024-03-08T00:00:00.000Z"},{"name":"WWE 2K24","uid":"164e4b7f-1bcd-53b9-bd82-2fb5740ae932","platforms":[{"name":"Playstation 5","shortName":"PS5"},{"name":"Xbox Series X/S","shortName":"XBS"},{"name":"Playstation 4","shortName":"PS4"},{"name":"Xbox One","shortName":"XBO"},{"name":"Microsoft Windows","shortName":"Win"}],"releaseDate":"2024-03-08T00:00:00.000Z"},{"name":"Contra: Operation Galuga","uid":"77d64e7b-4568-5b49-9af3-b8135ba5d00a","platforms":[{"name":"Playstation 5","shortName":"PS5"},{"name":"Xbox Series X/S","shortName":"XBS"},{"name":"Playstation 4","shortName":"PS4"},{"name":"Xbox One","shortName":"XBO"},{"name":"Nintendo Switch","shortName":"NS"},{"name":"Microsoft Windows","shortName":"Win"}],"releaseDate":"2024-03-12T00:00:00.000Z"},{"name":"Melatonin","uid":"363bbbe2-c3d8-5162-8887-ea71b7a944ac","platforms":[{"name":"Playstation 5","shortName":"PS5"}],"releaseDate":"2024-03-12T00:00:00.000Z"},{"name":"Passing By - A Tailwind Journey","uid":"a5c5887c-9bb5-51e2-9318-ab947b6562cf","platforms":[{"name":"Nintendo Switch","shortName":"NS"},{"name":"Microsoft Windows","shortName":"Win"}],"releaseDate":"2024-03-12T00:00:00.000Z"},{"name":"Llamasoft: The Jeff Minter Story","uid":"f105964c-ce4e-5617-adc9-f3cc4287a72d","platforms":[{"name":"Microsoft Windows","shortName":"Win"}],"releaseDate":"2024-03-13T00:00:00.000Z"},{"developer":"THA","name":"Humanity","publisher":"Enhance","uid":"9f1e6866-b652-5451-aaa4-90890487dadc","platforms":[{"name":"Oculus Quest","shortName":"OQ"}],"releaseDate":"2024-03-14T00:00:00.000Z"},{"name":"Cartel Tycoon","uid":"7d926445-c877-58de-825c-f5f26ec33895","platforms":[{"name":"Playstation 5","shortName":"PS5"},{"name":"Xbox Series X/S","shortName":"XBS"}],"releaseDate":"2024-03-14T00:00:00.000Z"},{"name":"Gylt","uid":"a6b54dce-ca1e-5b6a-b36f-32c014791dee","platforms":[{"name":"Nintendo Switch","shortName":"NS"}],"releaseDate":"2024-03-14T00:00:00.000Z"},{"name":"Highwater","uid":"16425cde-8f12-5500-8848-1b0694006d21","platforms":[{"name":"Playstation 5","shortName":"PS5"},{"name":"Xbox Series X/S","shortName":"XBS"},{"name":"Playstation 4","shortName":"PS4"},{"name":"Xbox One","shortName":"XBO"},{"name":"Nintendo Switch","shortName":"NS"},{"name":"Microsoft Windows","shortName":"Win"}],"releaseDate":"2024-03-14T00:00:00.000Z"},{"name":"Ib","uid":"3c7da7c8-2cd8-572d-926c-f960e5a826cc","platforms":[{"name":"Playstation 5","shortName":"PS5"},{"name":"Playstation 4","shortName":"PS4"}],"releaseDate":"2024-03-14T00:00:00.000Z"},{"name":"Lawn Mowing Simulator","uid":"22bf9c13-742e-591d-a54e-76fda8ce04bd","platforms":[{"name":"Nintendo Switch","shortName":"NS"}],"releaseDate":"2024-03-14T00:00:00.000Z"},{"name":"Star Wars: Battlefront Classic Collection","uid":"30e1ebc5-81d3-54d2-a768-a26f86424e0a","platforms":[{"name":"Playstation 5","shortName":"PS5"},{"name":"Xbox Series X/S","shortName":"XBS"},{"name":"Playstation 4","shortName":"PS4"},{"name":"Xbox One","shortName":"XBO"},{"name":"Nintendo Switch","shortName":"NS"},{"name":"Microsoft Windows","shortName":"Win"}],"releaseDate":"2024-03-14T00:00:00.000Z"},{"name":"The Vale: Shadow of the Crown","uid":"c3b69396-b91b-5096-bce9-37316e7c39db","platforms":[{"name":"Playstation 5","shortName":"PS5"},{"name":"Playstation 4","shortName":"PS4"},{"name":"Nintendo Switch","shortName":"NS"}],"releaseDate":"2024-03-14T00:00:00.000Z"},{"name":"What the Golf?","uid":"c327bd2c-3649-5abf-be04-78886910aedf","platforms":[{"name":"Playstation 5","shortName":"PS5"},{"name":"Playstation 4","shortName":"PS4"}],"releaseDate":"2024-03-14T00:00:00.000Z"},{"name":"Kingdom Come: Deliverance - Royal Edition","uid":"155c73e4-68d7-5cc1-ac37-a8c1b43b3e3d","platforms":[{"name":"Nintendo Switch","shortName":"NS"}],"releaseDate":"2024-03-15T00:00:00.000Z"},{"name":"Outcast: A New Beginning","uid":"c9bb8307-b14b-5fcd-acda-597332f1206c","platforms":[{"name":"Playstation 5","shortName":"PS5"},{"name":"Xbox Series X/S","shortName":"XBS"},{"name":"Microsoft Windows","shortName":"Win"}],"releaseDate":"2024-03-15T00:00:00.000Z"},{"name":"Hades","uid":"4d2c2fb2-f71e-5b14-83d5-e94b01a14f5c","platforms":[{"name":"iOS","shortName":"iOS"}],"releaseDate":"2024-03-19T00:00:00.000Z"},{"name":"Hi-Fi Rush","uid":"f1fd5d73-5b7a-51c9-87ee-4d2e3498618c","platforms":[{"name":"Playstation 5","shortName":"PS5"}],"releaseDate":"2024-03-19T00:00:00.000Z"},{"name":"MLB The Show 24","uid":"fc8b9f14-ea00-597f-9950-182c69e36ee0","platforms":[{"name":"Playstation 5","shortName":"PS5"},{"name":"Xbox Series X/S","shortName":"XBS"},{"name":"Playstation 4","shortName":"PS4"},{"name":"Xbox One","shortName":"XBO"},{"name":"Nintendo Switch","shortName":"NS"}],"releaseDate":"2024-03-19T00:00:00.000Z"},{"name":"Alone in the Dark (2024)","uid":"6b3f9edd-80b7-5ff9-85f4-3a3b8f9e27e9","platforms":[{"name":"Playstation 5","shortName":"PS5"},{"name":"Xbox Series X/S","shortName":"XBS"},{"name":"Microsoft Windows","shortName":"Win"}],"releaseDate":"2024-03-20T00:00:00.000Z"},{"name":"Call of Duty: Warzone Mobile","uid":"3587265f-9b49-53ae-84be-be9563c9bb28","platforms":[{"name":"iOS","shortName":"iOS"},{"name":"Android","shortName":"Droid"}],"releaseDate":"2024-03-21T00:00:00.000Z"},{"name":"Final Fantasy XIV: A Realm Reborn","uid":"a296b787-c5c6-56ec-a466-abfc7aa27d62","platforms":[{"name":"Xbox Series X/S","shortName":"XBS"}],"releaseDate":"2024-03-21T00:00:00.000Z"},{"name":"Final Fantasy XIV: Endwalker","uid":"4626c21f-9f0e-51d1-9809-a62c399500b7","platforms":[{"name":"Xbox Series X/S","shortName":"XBS"}],"releaseDate":"2024-03-21T00:00:00.000Z"},{"name":"Final Fantasy XIV: Heavensward","uid":"0ef29c78-1a41-5729-971f-e0c88a054ed6","platforms":[{"name":"Xbox Series X/S","shortName":"XBS"}],"releaseDate":"2024-03-21T00:00:00.000Z"},{"name":"Final Fantasy XIV: Shadowbringers","uid":"caab7f5b-fb3d-5b1f-a8dd-002a39f2530d","platforms":[{"name":"Xbox Series X/S","shortName":"XBS"}],"releaseDate":"2024-03-21T00:00:00.000Z"},{"name":"Final Fantasy XIV: Stormblood","uid":"301a9a4e-ca05-5c44-8246-c2f1eb4fc78f","platforms":[{"name":"Xbox Series X/S","shortName":"XBS"}],"releaseDate":"2024-03-21T00:00:00.000Z"},{"name":"Horizon Forbidden West","uid":"5c5ddb85-c3b6-5518-aeda-28a8a53d342d","platforms":[{"name":"Microsoft Windows","shortName":"Win"}],"releaseDate":"2024-03-21T00:00:00.000Z"},{"name":"Midnight Ghost Hunt","uid":"708ef29d-ce8b-5777-b9cd-0f460f787a29","platforms":[{"name":"Microsoft Windows","shortName":"Win"}],"releaseDate":"2024-03-21T00:00:00.000Z"},{"name":"Dragon's Dogma 2","uid":"fa307d46-fcca-55da-91b7-af8945bf6202","platforms":[{"name":"Playstation 5","shortName":"PS5"},{"name":"Xbox Series X/S","shortName":"XBS"},{"name":"Microsoft Windows","shortName":"Win"}],"releaseDate":"2024-03-22T00:00:00.000Z"},{"name":"Princess Peach: Showtime","uid":"47b591f3-fe83-529e-be83-f9e8bd75a1c5","platforms":[{"name":"Nintendo Switch","shortName":"NS"}],"releaseDate":"2024-03-22T00:00:00.000Z"},{"name":"Rise of the Rōnin","uid":"17c8d7ea-2886-59a4-9264-cfb925433584","platforms":[{"name":"Playstation 5","shortName":"PS5"}],"releaseDate":"2024-03-22T00:00:00.000Z"},{"name":"Palia","uid":"b8bca519-b2d5-545e-a468-88f9bf59eb1b","platforms":[{"name":"Microsoft Windows","shortName":"Win"}],"releaseDate":"2024-03-24T00:00:00.000Z"},{"name":"Acolyte of the Altar","uid":"d2b6d889-47c4-51fe-b01c-8426e84d373a","platforms":[{"name":"Microsoft Windows","shortName":"Win"}],"releaseDate":"2024-03-25T00:00:00.000Z"},{"name":"Bulwark: Falconeer Chronicles","uid":"be3388c3-63dd-5de3-a0c9-fd1fd05ed3d0","platforms":[{"name":"Playstation 5","shortName":"PS5"},{"name":"Xbox Series X/S","shortName":"XBS"},{"name":"Microsoft Windows","shortName":"Win"}],"releaseDate":"2024-03-26T00:00:00.000Z"},{"name":"Grandia HD Collection","uid":"603264a4-833d-51ad-993a-e06e06df05af","platforms":[{"name":"Playstation 4","shortName":"PS4"},{"name":"Xbox One","shortName":"XBO"}],"releaseDate":"2024-03-26T00:00:00.000Z"},{"name":"Planet Zoo: Console Edition","uid":"6cda5b90-7f5b-54f0-bbd1-3006db44f7fa","platforms":[{"name":"Playstation 5","shortName":"PS5"},{"name":"Xbox Series X/S","shortName":"XBS"}],"releaseDate":"2024-03-26T00:00:00.000Z"},{"name":"South Park: Snow Day!","uid":"5766a627-466d-5a2a-9492-3c85a4b0a880","platforms":[{"name":"Playstation 5","shortName":"PS5"},{"name":"Xbox Series X/S","shortName":"XBS"},{"name":"Nintendo Switch","shortName":"NS"},{"name":"Microsoft Windows","shortName":"Win"}],"releaseDate":"2024-03-26T00:00:00.000Z"},{"name":"The Last Case of Benedict Fox","uid":"2d9741f9-e84a-576f-a712-cc6ad64c04f9","platforms":[{"name":"Playstation 5","shortName":"PS5"}],"releaseDate":"2024-03-26T00:00:00.000Z"},{"name":"Ghost Trick: Phantom Detective","uid":"0b5ec661-e003-5c52-abb1-d822b79aaa34","platforms":[{"name":"Android","shortName":"Droid"}],"releaseDate":"2024-03-28T00:00:00.000Z"},{"name":"Open Roads","uid":"3d9bda95-0ccd-5ee5-835a-51db4ac15b52","platforms":[{"name":"Playstation 5","shortName":"PS5"},{"name":"Xbox Series X/S","shortName":"XBS"},{"name":"Playstation 4","shortName":"PS4"},{"name":"Xbox One","shortName":"XBO"},{"name":"Nintendo Switch","shortName":"NS"},{"name":"Microsoft Windows","shortName":"Win"}],"releaseDate":"2024-03-28T00:00:00.000Z"},{"name":"Outward","uid":"825d0bc1-041a-5c7c-b6ec-4a9b5a191951","platforms":[{"name":"Nintendo Switch","shortName":"NS"}],"releaseDate":"2024-03-28T00:00:00.000Z"},{"name":"Pepper Grinder","uid":"c6f3b8e7-0441-5c94-9fad-21599bc77d78","platforms":[{"name":"Nintendo Switch","shortName":"NS"},{"name":"Microsoft Windows","shortName":"Win"}],"releaseDate":"2024-03-28T00:00:00.000Z"}],"index":2,"name":"March","updatedAt":"2024-05-09T01:09:09.283Z"}